dataguzzler_python/NOTES.txt
dataguzzler_python/OpaqueWrapper.py
dataguzzler_python/Qt.dpi
dataguzzler_python/Qt.py
dataguzzler_python/QtConfig.py
dataguzzler_python/QtWrapper.py
dataguzzler_python/__init__.pxd
dataguzzler_python/__init__.py
dataguzzler_python/_version.py
dataguzzler_python/async_conn.py
dataguzzler_python/auth.py
dataguzzler_python/awaittest.py
dataguzzler_python/censoring.py
dataguzzler_python/configfile.py
dataguzzler_python/configfile_utils.py
dataguzzler_python/conn.py
dataguzzler_python/context.py
dataguzzler_python/dg_internal.pxd
dataguzzler_python/dgold.c
dataguzzler_python/dgold.h
dataguzzler_python/dgold.pxd
dataguzzler_python/dgold.pyx
dataguzzler_python/dgold_locking_c.c
dataguzzler_python/dgold_locking_c.h
dataguzzler_python/dgold_module_c.c
dataguzzler_python/dgold_module_c.h
dataguzzler_python/dgold_rpc_c.c
dataguzzler_python/dgpy.py
dataguzzler_python/dgpy_dgold.dpi
dataguzzler_python/dgpy_startup.dpi
dataguzzler_python/dynamic_metadata.py
dataguzzler_python/error_console.dpi
dataguzzler_python/error_console.py
dataguzzler_python/gpib.dpi
dataguzzler_python/help.py
dataguzzler_python/lock.py
dataguzzler_python/main_thread.py
dataguzzler_python/mainloop.py
dataguzzler_python/matplotlib.dpi
dataguzzler_python/motion_controller.py
dataguzzler_python/network_access.dpi
dataguzzler_python/pint.dpi
dataguzzler_python/remoteproxy.py
dataguzzler_python/savewfm.c
dataguzzler_python/savewfm.pyx
dataguzzler_python/savewfm_c.h
dataguzzler_python/serial.dpi
dataguzzler_python/serial.py
dataguzzler_python/serial_device.dpi
dataguzzler_python/subproc.py
dataguzzler_python/visa.dpi
dataguzzler_python/visa.py
dataguzzler_python/visa_device.dpi
dataguzzler_python/wfmstore.i
dataguzzler_python/wfmstore.pxd
dataguzzler_python/bin/__init__.py
dataguzzler_python/bin/dataguzzler_python.py
dataguzzler_python/bin/dgpy.py
dataguzzler_python/modules/__init__.py
dataguzzler_python/modules/dmx_usb_pro.py
dataguzzler_python/modules/motion_control/__init__.py
dataguzzler_python-0.4.1.dist-info/METADATA
dataguzzler_python-0.4.1.dist-info/WHEEL
dataguzzler_python-0.4.1.dist-info/entry_points.txt
dataguzzler_python-0.4.1.dist-info/top_level.txt
dataguzzler_python-0.4.1.dist-info/RECORD
