Metadata-Version: 2.2
Name: dataguzzler-python
Version: 0.4.1
Summary: dataguzzler-python
Home-page: http://thermal.cnde.iastate.edu
Author: Stephen D. Holland
Classifier: Development Status :: 3 - Alpha
Classifier: License :: OSI Approved :: BSD License
Requires-Python: >=3.8
Dynamic: author
Dynamic: home-page
Dynamic: summary
